nextcloud_mcp/__init__.py
nextcloud_mcp/config.py
nextcloud_mcp/context.py
nextcloud_mcp/exceptions.py
nextcloud_mcp-0.1.0.dist-info/METADATA
nextcloud_mcp-0.1.0.dist-info/WHEEL
nextcloud_mcp-0.1.0.dist-info/RECORD
