Metadata-Version: 2.4
Name: nextcloud-mcp
Version: 0.1.0
Summary: A Model-Context-Protocol (MCP) for saving files to Nextcloud and getting public share links.
Author-email: Gemini Code Assist <author@example.com>
Classifier: License :: OSI Approved :: Apache Software License
Classifier: Operating System :: OS Independent
Classifier: Programming Language :: Python :: 3
Requires-Python: >=3.8
Requires-Dist: httpx[http2]>=0.27.0
Requires-Dist: python-dotenv>=1.0.0
Provides-Extra: test
Requires-Dist: pytest-asyncio>=0.20.0; extra == 'test'
Requires-Dist: pytest>=7.0.0; extra == 'test'
